fichier/__init__.py
fichier/chmod.py
fichier/clean.py
fichier/cli.py
fichier/dependencies.py
fichier/license.py
fichier/perm.py
fichier/structure.py
fichier/tmp.py
fichierfr-0.1.0.dist-info/licenses/LICENSE
fichierfr-0.1.0.dist-info/METADATA
fichierfr-0.1.0.dist-info/WHEEL
fichierfr-0.1.0.dist-info/entry_points.txt
fichierfr-0.1.0.dist-info/top_level.txt
fichierfr-0.1.0.dist-info/RECORD
