Metadata-Version: 2.4
Name: fichierfr
Version: 0.1.0
Summary: Outils avancés pour la gestion de fichiers et répertoires
Author: GameurDev
Requires-Python: >=3.6
License-File: LICENSE
Dynamic: license-file
